jobpilot/__init__.py
jobpilot/models/__init__.py
jobpilot/models/company.py
jobpilot/models/job.py
jobpilot/models/location.py
jobpilot/py.typed
jobpilot/scrapers/__init__.py
jobpilot/scrapers/base.py
jobpilot/scrapers/linkedin.py
jobpilot-0.5.1.dist-info/LICENSE
jobpilot-0.5.1.dist-info/METADATA
jobpilot-0.5.1.dist-info/WHEEL
jobpilot-0.5.1.dist-info/RECORD
