Metadata-Version: 2.1
Name: jobpilot
Version: 0.5.1
Summary: Job scraper
Author: fabifont
Author-email: me@fabifont.dev
Requires-Python: >=3.11,<4.0
Classifier: Programming Language :: Python :: 3
Classifier: Programming Language :: Python :: 3.11
Classifier: Programming Language :: Python :: 3.12
Requires-Dist: aiolimiter (>=1.1.0,<2.0.0)
Requires-Dist: beautifulsoup4 (>=4.12.2,<5.0.0)
Requires-Dist: httpx (>=0.25.0,<0.26.0)
Requires-Dist: loguru (>=0.7.2,<0.8.0)
Requires-Dist: lxml (>=4.9.3,<5.0.0)
Requires-Dist: pydantic (>=2.4.2,<3.0.0)
